near_abi_py/__init__.py
near_abi_py/abi_schema.json
near_abi_py/cli.py
near_abi_py/core.py
near_abi_py/generator.py
near_abi_py/py.typed
near_abi_py/utils.py
near_abi_py-1.0.0.dist-info/METADATA
near_abi_py-1.0.0.dist-info/WHEEL
near_abi_py-1.0.0.dist-info/entry_points.txt
near_abi_py-1.0.0.dist-info/licenses/LICENSE
near_abi_py-1.0.0.dist-info/RECORD
