Metadata-Version: 2.4
Name: near-abi-py
Version: 1.0.0
Summary: ABI Builder for NEAR Python Smart Contracts
License-File: LICENSE
Requires-Python: >=3.12
Requires-Dist: click>=8.1.8
Requires-Dist: jsonschema>=4.23.0
Requires-Dist: pathspec>=0.12.1
Requires-Dist: pydantic>=2.10.6
Requires-Dist: rich>=13.9.4
